equolver/__init__.py
equolver/beach.py
equolver-0.0.11.data/scripts/equolver
equolver-0.0.11.dist-info/LICENSE
equolver-0.0.11.dist-info/METADATA
equolver-0.0.11.dist-info/WHEEL
equolver-0.0.11.dist-info/top_level.txt
equolver-0.0.11.dist-info/RECORD
