Metadata-Version: 2.1
Name: equolver
Version: 0.0.11
Summary: Development Status :: 4 - Beta
Home-page: https://github.com/gigjozsa/equolver
Author: Gyula Jozsa
Author-email: gigjozsast@gmail.com
License: BSD 3-Clause License
Platform: UNKNOWN
Classifier: Development Status :: 4 - Beta
Classifier: Intended Audience :: Science/Research
Classifier: License :: OSI Approved :: BSD License
Classifier: Operating System :: POSIX :: Linux
Classifier: Programming Language :: Python
Classifier: Topic :: Scientific/Engineering :: Astronomy
Requires-Python: >=3.6
License-File: LICENSE
Requires-Dist: numpy
Requires-Dist: scipy
Requires-Dist: astropy
Requires-Dist: radio-beam
Requires-Dist: pyfftw
Requires-Dist: bokeh
Provides-Extra: testing
Requires-Dist: pytest (>=6.0.0) ; extra == 'testing'
